primers/__init__.py
primers/main.py
primers/off_targets.py
primers/primers.py
tests/__init__.py
tests/off_targets_test.py
tests/primers_test.py
primers-0.5.10.dist-info/LICENSE
primers-0.5.10.dist-info/METADATA
primers-0.5.10.dist-info/WHEEL
primers-0.5.10.dist-info/entry_points.txt
primers-0.5.10.dist-info/top_level.txt
primers-0.5.10.dist-info/RECORD
