Metadata-Version: 2.1
Name: primers
Version: 0.5.10
Summary: Create PCR primers with optimal lengths, tms, gc%s and free energies
Home-page: https://github.com/Lattice-Automation/primers
Author: JJTimmons
Author-email: jtimmons@latticeautomation.com
License: mit
Platform: UNKNOWN
Classifier: Development Status :: 3 - Alpha
Classifier: Programming Language :: Python :: 3 :: Only
Classifier: Topic :: Scientific/Engineering :: Bio-Informatics
Classifier: Environment :: Console
Requires-Python: >=3.0
License-File: LICENSE
Requires-Dist: seqfold (>=0.7.3)
